watchmen_indicator_kernel/__init__.py
watchmen_indicator_kernel/common/__init__.py
watchmen_indicator_kernel/common/exception.py
watchmen_indicator_kernel/common/settings.py
watchmen_indicator_kernel/data/__init__.py
watchmen_indicator_kernel/data/convergence/__init__.py
watchmen_indicator_kernel/data/convergence/data_helper.py
watchmen_indicator_kernel/data/convergence/data_service.py
watchmen_indicator_kernel/data/objective/__init__.py
watchmen_indicator_kernel/data/objective/data_helper.py
watchmen_indicator_kernel/data/objective/data_service.py
watchmen_indicator_kernel/data/objective_factor/__init__.py
watchmen_indicator_kernel/data/objective_factor/data_helper.py
watchmen_indicator_kernel/data/objective_factor/data_service.py
watchmen_indicator_kernel/data/objective_factor/objective_criteria_service.py
watchmen_indicator_kernel/data/objective_factor/subject_base_service.py
watchmen_indicator_kernel/data/objective_factor/topic_base_service.py
watchmen_indicator_kernel/data/utils/__init__.py
watchmen_indicator_kernel/data/utils/bucket.py
watchmen_indicator_kernel/data/utils/derived_objective.py
watchmen_indicator_kernel/data/utils/enum.py
watchmen_indicator_kernel/data/utils/factor.py
watchmen_indicator_kernel/data/utils/indicator.py
watchmen_indicator_kernel/data/utils/parameter.py
watchmen_indicator_kernel/data/utils/subject.py
watchmen_indicator_kernel/data/utils/time_frame.py
watchmen_indicator_kernel/data/utils/topic.py
watchmen_indicator_kernel/meta/__init__.py
watchmen_indicator_kernel/meta/achievement_task_service.py
watchmen_indicator_kernel/meta/bucket_service.py
watchmen_indicator_kernel/meta/convergence_service.py
watchmen_indicator_kernel/meta/derived_objective_report_service.py
watchmen_indicator_kernel/meta/derived_objective_service.py
watchmen_indicator_kernel/meta/indicator_service.py
watchmen_indicator_kernel/meta/objective_report_service.py
watchmen_indicator_kernel/meta/objective_service.py
watchmen_indicator_kernel/plugin/__init__.py
watchmen_indicator_kernel-18.0.1.dist-info/METADATA
watchmen_indicator_kernel-18.0.1.dist-info/WHEEL
watchmen_indicator_kernel-18.0.1.dist-info/RECORD
